analysis_lib/__init__.py
analysis_lib/config.py
analysis_lib/csaf.py
analysis_lib/normalize.py
analysis_lib/output.py
analysis_lib/reachability.py
analysis_lib/search.py
analysis_lib/utils.py
analysis_lib/vdr.py
ds_analysis_lib-6.0.0.dist-info/METADATA
ds_analysis_lib-6.0.0.dist-info/WHEEL
ds_analysis_lib-6.0.0.dist-info/top_level.txt
ds_analysis_lib-6.0.0.dist-info/RECORD
